ilexconf/__init__.py
ilexconf/adapters/__init__.py
ilexconf/adapters/argparse.py
ilexconf/adapters/common/__init__.py
ilexconf/adapters/common/address.py
ilexconf/adapters/common/decorators.py
ilexconf/adapters/env.py
ilexconf/adapters/ini.py
ilexconf/adapters/json.py
ilexconf/adapters/yaml.py
ilexconf/config.py
ilexconf/config.txt
ilexconf/console/__init__.py
ilexconf/console/application.py
ilexconf/console/commands/__init__.py
ilexconf/console/commands/common_arguments.py
ilexconf/console/commands/common_options.py
ilexconf/console/commands/config.py
ilexconf/console/commands/convert.py
ilexconf/console/commands/get.py
ilexconf/console/commands/list.py
ilexconf/console/commands/set.py
ilexconf/tests/__init__.py
ilexconf/tests/adapters/common/test_address.py
ilexconf/tests/adapters/common/test_address_resolver.py
ilexconf/tests/adapters/common/test_decorators.py
ilexconf/tests/adapters/test_env.py
ilexconf/tests/adapters/test_ini.py
ilexconf/tests/adapters/test_json.py
ilexconf/tests/adapters/test_yaml.py
ilexconf/tests/config/test_basics.py
ilexconf/tests/conftest.py
ilexconf/tests/debug.py
ilexconf/tests/examples/test_index.py
ilexconf/tests/examples/test_quick_start.py
ilexconf/tests/resources/ini/sample.ini
ilexconf/tests/resources/ini/sample.json
ilexconf/tests/resources/settings.json
ilexconf/tests/resources/yaml/simple.json
ilexconf/tests/resources/yaml/simple.yaml
ilexconf-0.9.6.dist-info/entry_points.txt
ilexconf-0.9.6.dist-info/WHEEL
ilexconf-0.9.6.dist-info/METADATA
ilexconf-0.9.6.dist-info/RECORD
