Metadata-Version: 2.1
Name: ilexconf
Version: 0.9.6
Summary: Configuration library for Python 🔧 Load from multiple sources
Home-page: https://github.com/ilexconf/ilexconf
License: MIT
Keywords: configuration,settings,json,yaml,ini
Author: vduseev
Author-email: vagiz@duseev.com
Maintainer: vduseev
Maintainer-email: vagiz@duseev.com
Requires-Python: >=3.8,<4.0
Classifier: License :: OSI Approved :: MIT License
Classifier: Programming Language :: Python :: 3
Classifier: Programming Language :: Python :: 3.8
Classifier: Programming Language :: Python :: 3.9
Provides-Extra: console
Provides-Extra: yaml
Requires-Dist: cleo (>=0.8.1,<0.9.0); extra == "console"
Requires-Dist: mapz (>=1.1.28,<2.0.0)
Requires-Dist: ruamel.yaml (>=0.16.12,<0.17.0); extra == "yaml"
Project-URL: Documentation, https://ilexconf.com
Project-URL: Repository, https://github.com/ilexconf/ilexconf
